README.md
setup.cfg
setup.py
thampi/__init__.py
thampi.egg-info/PKG-INFO
thampi.egg-info/SOURCES.txt
thampi.egg-info/dependency_links.txt
thampi.egg-info/entry_points.txt
thampi.egg-info/not-zip-safe
thampi.egg-info/requires.txt
thampi.egg-info/top_level.txt
thampi/cli/__init__.py
thampi/cli/cli.py
thampi/cli/commands.py
thampi/core/__init__.py
thampi/core/api.py
thampi/core/constants.py
thampi/core/flask_api.py
thampi/core/helper.py
thampi/core/model.py
thampi/core/thampi_core.py
thampi/lib/__init__.py
thampi/lib/aws.py
thampi/lib/util.py