Metadata-Version: 1.1
Name: thampi
Version: 0.1.0
Summary: Create a Machine Learning Prediction Server on AWS Lambda.
Home-page: https://github.com/scoremedia/thampi
Author: theScore Inc.
Author-email: oss@thescore.com
License: BSD
Platform: any
Classifier: Development Status :: 4 - Beta
Classifier: Environment :: Console
Classifier: Intended Audience :: Developers
Classifier: License :: OSI Approved :: Apache Software License
Classifier: Operating System :: POSIX
Classifier: Operating System :: MacOS
Classifier: Operating System :: Unix
Classifier: Operating System :: Microsoft :: Windows
Classifier: Programming Language :: Python
Classifier: Programming Language :: Python :: 3
Classifier: Topic :: Software Development :: Libraries :: Python Modules
